{
    "hidden_dims": 128,
    "num_episodes": 100000,
    "batch_size": 64,
    "epsilon_fn": "linear",
    "epsilon_lin_start": 1.0,
    "epsilon_lin_end": 0.01,
    "replaybuffer_capacity": 500000,
    "gamma": 0.99,
    "lr": 0.0001,
    "tau": 0.005,
    "data_file": "course_bbb_2013b-train.csv",
    "categories_range_start": 50,
    "categories_range_end": 91,
    "grade_boundaries": 10,
    "simulator": "gyms.simulator_D_credits_grouped",
    "num_categories": 6,
    "epsilon_decay": 75000.0,
    "max_sequence_length": 17,
    "average_reward": 2.50516,
    "average_reward_last_half": 3.15408,
    "average_reward_last_100": 3.43,
    "elapsed_time": 4000.7175047397614
}